ubt_runtime/__init__.py
ubt_runtime/darwin_aarch64/pyarmor_runtime.so
ubt_runtime/darwin_x86_64/pyarmor_runtime.so
ubt_runtime/freebsd_x86_64/pyarmor_runtime.so
ubt_runtime/linux_aarch64/pyarmor_runtime.so
ubt_runtime/linux_x86_64/pyarmor_runtime.so
ubt_runtime/windows_x86_64/pyarmor_runtime.pyd
ubt_runtime-0.4.0.dist-info/licenses/LICENSE
ubt_runtime-0.4.0.dist-info/WHEEL
ubt_runtime-0.4.0.dist-info/METADATA
ubt_runtime-0.4.0.dist-info/RECORD
